dataAccess/EquityApi.py
dataAccess/EtdApi.py
dataAccess/EtdHistoryApi.py
dataAccess/EtdUtil.py
dataAccess/__init__.py
ReferenceDataAccess-0.1.1.dist-info/METADATA
ReferenceDataAccess-0.1.1.dist-info/WHEEL
ReferenceDataAccess-0.1.1.dist-info/top_level.txt
ReferenceDataAccess-0.1.1.dist-info/RECORD
