Metadata-Version: 2.1
Name: ReferenceDataAccess
Version: 0.1.1
Summary: A python library to easily fetch reference data from RduAccess and integrate it with your python application
Author: Jay Sangoi
Author-email: jay.sangoi@gmail.com
License: MIT
Keywords: stocks,market,finance,RduAccess,quotes,derivatives,equity,fixed income,Mifid,shares,Reference Data,isin,sedol,id_bb_global
Classifier: Programming Language :: Python :: 3
Classifier: Intended Audience :: Developers
Classifier: License :: OSI Approved :: MIT License
Classifier: Topic :: Office/Business :: Financial :: Investment
Classifier: Operating System :: OS Independent
Requires-Python: >=3.6
Requires-Dist: requests
